{
  "id": 11,
  "name": "Level 11 — The Last Crystal",
  "isBoss": true,
  "grid": [
    [
      1,
      1,
      1,
      1,
      1,
      1,
      1,
      1,
      1,
      1,
      1,
      1,
      1,
      1,
      1
    ],
    [
      1,
      1,
      1,
      1,
      1,
      1,
      1,
      1,
      1,
      1,
      1,
      1,
      1,
      1,
      1
    ],
    [
      1,
      1,
      1,
      1,
      1,
      0,
      0,
      0,
      0,
      0,
      0,
      1,
      1,
      1,
      1
    ],
    [
      1,
      1,
      1,
      1,
      1,
      1,
      1,
      0,
      1,
      1,
      1,
      1,
      1,
      1,
      1
    ],
    [
      1,
      1,
      1,
      1,
      1,
      1,
      1,
      0,
      1,
      1,
      1,
      1,
      1,
      1,
      1
    ],
    [
      1,
      1,
      1,
      1,
      1,
      1,
      1,
      0,
      1,
      1,
      1,
      1,
      1,
      1,
      1
    ],
    [
      1,
      1,
      1,
      1,
      1,
      1,
      1,
      0,
      1,
      1,
      1,
      1,
      1,
      1,
      1
    ],
    [
      1,
      1,
      1,
      1,
      1,
      0,
      0,
      0,
      1,
      1,
      1,
      1,
      1,
      1,
      1
    ],
    [
      1,
      1,
      1,
      1,
      1,
      0,
      0,
      0,
      1,
      1,
      1,
      1,
      1,
      1,
      1
    ],
    [
      1,
      1,
      1,
      1,
      1,
      1,
      1,
      1,
      1,
      1,
      1,
      1,
      1,
      1,
      1
    ]
  ],
  "start": {
    "x": 7,
    "y": 8
  },
  "enemies": [
    {
      "id": "boss",
      "x": 7,
      "y": 2,
      "hp": 67
    },
    {
      "id": "e11-1-1782636067509",
      "x": 5,
      "y": 2,
      "hp": 1
    },
    {
      "id": "e11-2-1782636069285",
      "x": 10,
      "y": 2,
      "hp": 1
    },
    {
      "id": "e11-3-1782636069784",
      "x": 9,
      "y": 2,
      "hp": 1
    },
    {
      "id": "e11-4-1782636070133",
      "x": 8,
      "y": 2,
      "hp": 1
    },
    {
      "id": "e11-5-1782636070791",
      "x": 6,
      "y": 2,
      "hp": 1
    }
  ],
  "crystalPath": [
    {
      "x": 7,
      "y": 7
    },
    {
      "x": 7,
      "y": 6
    },
    {
      "x": 7,
      "y": 5
    },
    {
      "x": 7,
      "y": 5
    },
    {
      "x": 7,
      "y": 4
    },
    {
      "x": 7,
      "y": 5
    },
    {
      "x": 7,
      "y": 6
    },
    {
      "x": 7,
      "y": 6
    },
    {
      "x": 7,
      "y": 7
    },
    {
      "x": 7,
      "y": 4
    },
    {
      "x": 7,
      "y": 5
    }
  ]
}